meshzoo/__init__.py
meshzoo/_ball.py
meshzoo/_cube.py
meshzoo/_disk.py
meshzoo/_helpers.py
meshzoo/_license_validation.py
meshzoo/_moebius.py
meshzoo/_ngon.py
meshzoo/_platonic.py
meshzoo/_rectangle.py
meshzoo/_sphere.py
meshzoo/_triangle.py
meshzoo/_tube.py
meshzoo-0.11.6.dist-info/METADATA
meshzoo-0.11.6.dist-info/WHEEL
meshzoo-0.11.6.dist-info/top_level.txt
meshzoo-0.11.6.dist-info/RECORD
