Metadata-Version: 2.1
Name: meshzoo
Version: 0.11.6
Summary: Collection of explicitly constructed meshes
Author-email: Nico Schlömer <nico.schloemer@gmail.com>
Keywords: engineering,fem,finite elements,mesh,scientific
Classifier: Development Status :: 5 - Production/Stable
Classifier: Intended Audience :: Science/Research
Classifier: License :: Other/Proprietary License
Classifier: Operating System :: OS Independent
Classifier: Programming Language :: Python
Classifier: Programming Language :: Python :: 3 :: Only
Classifier: Programming Language :: Python :: 3.8
Classifier: Programming Language :: Python :: 3.9
Classifier: Programming Language :: Python :: 3.10
Classifier: Programming Language :: Python :: 3.11
Classifier: Programming Language :: Python :: 3.12
Classifier: Topic :: Scientific/Engineering
Classifier: Topic :: Scientific/Engineering :: Mathematics
Requires-Python: >=3.8
Requires-Dist: x21 (>=0.5.1)
Requires-Dist: numpy >=1.20
Requires-Dist: stonefish-license-manager >=0.4.33
Provides-Extra: all
Requires-Dist: matplotlib ; extra == 'all'
Provides-Extra: plot
Requires-Dist: matplotlib ; extra == 'plot'
